mycalc/calculator.py
sol230411-0.0.1.dist-info/METADATA
sol230411-0.0.1.dist-info/WHEEL
sol230411-0.0.1.dist-info/top_level.txt
sol230411-0.0.1.dist-info/RECORD
